Workbook

Sheet Comps Val
B1: INDIAN PHARMACEUTICALS | Q1: Shreya Sinha Roy
B2: Trading Comparbles and Relative Valuation | Q2: 46235
B3: Amount in crores | Market data as on 13th August 2026
B6: Comparable Company Valuation
D8: Market Data | K8: Financials | O8: Valuation
B9: Company | C9: Ticker | D9: Share Price | E9: Shares Outstanding | F9: Equity Value | G9: Net debt | H9: Enterprise Value | K9: Revenue | L9: EBITDA | M9: Net income | O9: EV/Revenue | P9: EV/EBITDA | Q9: P/E
B11: =Data!C6 -> Cipla | C11: CIPLA | D11: =Data!D6 -> 1461 | E11: =Data!E6 -> 80.78 | F11: =Data!F6 -> 118019.58 | G11: =Data!I6 -> -693.65 | H11: =Data!J6 -> 117325.93 | K11: =Data!K6 -> 28324.4 | L11: =Data!L6 -> 6131.41 | M11: =Data!M6 -> 3355.68 | O11: =$H11/K11 -> 4.1422212 | P11: =$H11/L11 -> 19.135228 | Q11: =F11/M11 -> 35.170094
B12: =Data!C3 -> Sun Pharma.Inds. | C12: SUNPHARMA | D12: =Data!D3 -> 1942.85 | E12: =Data!E3 -> 239.93 | F12: =Data!F3 -> 466148 | G12: =Data!I3 -> -6975.76 | H12: =Data!J3 -> 459172.24 | K12: =Data!K3 -> 59910.52 | L12: =Data!L3 -> 20078.29 | M12: =Data!M3 -> 12117.01 | O12: =$H12/K12 -> 7.6643007 | P12: =$H12/L12 -> 22.869091 | Q12: =F12/M12 -> 38.470547
B13: =Data!C4 -> Divi's Lab. | C13: DIVISLAB | D13: =Data!D4 -> 8500 | E13: =Data!E4 -> 26.55 | F13: =Data!F4 -> 225675 | G13: =Data!I4 -> -3407 | H13: =Data!J4 -> 222268 | K13: =Data!K4 -> 11230 | L13: =Data!L4 -> 4419 | M13: =Data!M4 -> 2925 | O13: =$H13/K13 -> 19.792342 | P13: =$H13/L13 -> 50.298258 | Q13: =F13/M13 -> 77.153846
B14: =Data!C5 -> Torrent Pharma. | C14: TORNTPHARM | D14: =Data!D5 -> 4876.3 | E14: =Data!E5 -> 38.04 | F14: =Data!F5 -> 185494.45 | G14: =Data!I5 -> 13860.3 | H14: =Data!J5 -> 199354.75 | K14: =Data!K5 -> 15723 | L14: =Data!L5 -> 5122 | M14: =Data!M5 -> 2156 | O14: =$H14/K14 -> 12.67918 | P14: =$H14/L14 -> 38.921271 | Q14: =F14/M14 -> 86.036388
B15: =Data!C7 -> Zydus Lifesci. | C15: ZYDUSLIFE | D15: =Data!D7 -> 1173 | E15: =Data!E7 -> 99.75 | F15: =Data!F7 -> 117006.75 | G15: =Data!I7 -> 11079.4 | H15: =Data!J7 -> 128086.15 | K15: =Data!K7 -> 28591.7 | L15: =Data!L7 -> 8776.7 | M15: =Data!M7 -> 4592.7 | O15: =$H15/K15 -> 4.4798368 | P15: =$H15/L15 -> 14.593885 | Q15: =F15/M15 -> 25.47668
B16: =Data!C8 -> Lupin | C16: LUPIN | D16: =Data!D8 -> 2261 | E16: =Data!E8 -> 45.72 | F16: =Data!F8 -> 103372.92 | G16: =Data!I8 -> 963.28 | H16: =Data!J8 -> 104336.2 | K16: =Data!K8 -> 29966.58 | L16: =Data!L8 -> 10014.02 | M16: =Data!M8 -> 5550.99 | O16: =$H16/K16 -> 3.481752 | P16: =$H16/L16 -> 10.419013 | Q16: =F16/M16 -> 18.62243
B17: =Data!C9 -> Dr Reddy's Labs | C17: DRREDDY | D17: =Data!D9 -> 1206 | E17: =Data!E9 -> 83.47 | F17: =Data!F9 -> 100664.82 | G17: =Data!I9 -> 4385.4 | H17: =Data!J9 -> 105050.22 | K17: =Data!K9 -> 33227.9 | L17: =Data!L9 -> 6576.6 | M17: =Data!M9 -> 3183.3 | O17: =$H17/K17 -> 3.1615064 | P17: =$H17/L17 -> 15.973333 | Q17: =F17/M17 -> 31.622788
B18: =Data!C10 -> Mankind Pharma | C18: MANKIND | D18: =Data!D10 -> 2418 | E18: =Data!E10 -> 41.3 | F18: =Data!F10 -> 99863.4 | G18: =Data!I10 -> 5828.77 | H18: =Data!J10 -> 105692.17 | K18: =Data!K10 -> 14737.88 | L18: =Data!L10 -> 4163.2 | M18: =Data!M10 -> 2067.57 | O18: =$H18/K18 -> 7.1714636 | P18: =$H18/L18 -> 25.387243 | Q18: =F18/M18 -> 48.299888
B19: =Data!C11 -> Laurus Labs | C19: LAURUSLABS | D19: =Data!D11 -> 1841.05 | E19: =Data!E11 -> 54.03 | F19: =Data!F11 -> 99471.932 | G19: =Data!I11 -> 2404.78 | H19: =Data!J11 -> 101876.71 | K19: =Data!K11 -> 7269.64 | L19: =Data!L11 -> 2087.55 | M19: =Data!M11 -> 1090.53 | O19: =$H19/K19 -> 14.013997 | P19: =$H19/L19 -> 48.802046 | Q19: =F19/M19 -> 91.214301
B20: =Data!C12 -> Aurobindo Pharma | C20: AUROPHARMA | D20: =Data!D12 -> 1656.6 | E20: =Data!E12 -> 58.08 | F20: =Data!F12 -> 96215.328 | G20: =Data!I12 -> -1797.45 | H20: =Data!J12 -> 94417.878 | K20: =Data!K12 -> 34935.29 | L20: =Data!L12 -> 7772.84 | M20: =Data!M12 -> 3710.8 | O20: =$H20/K20 -> 2.7026505 | P20: =$H20/L20 -> 12.147153 | Q20: =F20/M20 -> 25.92846
B22: High | O22: =MAX(O11:O20) -> 19.792342 | P22: =MAX(P11:P20) -> 50.298258 | Q22: =MAX(Q11:Q20) -> 91.214301
B23: 75th percentile | O23: =QUARTILE(O11:O20,3) -> 11.42546 | P23: =QUARTILE(P11:P20,3) -> 35.537764 | Q23: =QUARTILE(Q11:Q20,3) -> 69.940357
B24: Average | O24: =AVERAGE(O11:O20) -> 7.928925 | P24: =AVERAGE(P11:P20) -> 25.854652 | Q24: =AVERAGE(Q11:Q20) -> 47.799542
B25: Median | O25: =MEDIAN(O11:O20) -> 5.8256502 | P25: =MEDIAN(P11:P20) -> 21.00216 | Q25: =MEDIAN(Q11:Q20) -> 36.82032
B26: 25th percentile | O26: =QUARTILE(O11:O20,1) -> 3.6468693 | P26: =QUARTILE(P11:P20,1) -> 14.938747 | Q26: =QUARTILE(Q11:Q20,1) -> 27.352042
B27: Low | O27: =MIN(O11:O20) -> 2.7026505 | P27: =MIN(P11:P20) -> 10.419013 | Q27: =MIN(Q11:Q20) -> 18.62243
B29: Cipla Comparable Valuation | O29: EV/Revenue | P29: EV/EBITDA | Q29: P/E
B31: Implied Enterprise Value | O31: =O$25*K11 -> 165008.05 | P31: =P$25*L11 -> 128772.85 | Q31: =Q33+Q32 -> 122863.56
B32: Net Debt | O32: =$G$11 -> -693.65 | P32: =$G$11 -> -693.65 | Q32: =$G$11 -> -693.65
B33: Implied Market Value | O33: =O31-O32 -> 165701.7 | P33: =P31-P32 -> 129466.5 | Q33: =Q25*M11 -> 123557.21
B34: Shares Outstanding | O34: =$E$11 -> 80.78 | P34: =$E$11 -> 80.78 | Q34: =$E$11 -> 80.78
B35: Implied Value per share | O35: =O33/O34 -> 2051.2713 | P35: =P33/P34 -> 1602.7049 | Q35: =Q33/Q34 -> 1529.552
B37: Source: Screener.com
O38: =IF(O35>$D$11,"Undervalued","Overvalued") -> Undervalued | P38: =IF(P35>$D$11,"Undervalued","Overvalued") -> Undervalued | Q38: =IF(Q35>$D$11,"Undervalued","Overvalued") -> Undervalued

Sheet Data
B2: S.No. | C2: Name | D2: CMP Rs. | E2: No. Eq. Shares Cr. | F2: Market Cap | G2: Debt Rs.Cr. | H2: Cash End Rs.Cr. | I2: Net Debt | J2: EV | K2: Sales Rs.Cr. | L2: EBITDA | M2: NP 12M Rs.Cr. | N2: Mar Cap Rs.Cr.
B3: 1 | C3: Sun Pharma.Inds. | D3: 1942.85 | E3: 239.93 | F3: =D3*E3 -> 466148 | G3: 4627.32 | H3: 11603.08 | I3: =G3-H3 -> -6975.76 | J3: =F3+G3-H3 -> 459172.24 | K3: 59910.52 | L3: 20078.29 | M3: 12117.01 | N3: 466154.86
B4: 2 | C4: Divi's Lab. | D4: 8500 | E4: 26.55 | F4: =D4*E4 -> 225675 | G4: 7 | H4: 3414 | I4: =G4-H4 -> -3407 | J4: =F4+G4-H4 -> 222268 | K4: 11230 | L4: 4419 | M4: 2925 | N4: 227100.68
B5: 3 | C5: Torrent Pharma. | D5: 4876.3 | E5: 38.04 | F5: =D5*E5 -> 185494.45 | G5: 15025.5 | H5: 1165.2 | I5: =G5-H5 -> 13860.3 | J5: =F5+G5-H5 -> 199354.75 | K5: 15723 | L5: 5122 | M5: 2156 | N5: 185478.78
B6: 4 | C6: Cipla | D6: 1461 | E6: 80.78 | F6: =D6*E6 -> 118019.58 | G6: 613.77 | H6: 1307.42 | I6: =G6-H6 -> -693.65 | J6: =F6+G6-H6 -> 117325.93 | K6: 28324.4 | L6: 6131.41 | M6: 3355.68 | N6: 118143.29
B7: 5 | C7: Zydus Lifesci. | D7: 1173 | E7: 99.75 | F7: =D7*E7 -> 117006.75 | G7: 12496 | H7: 1416.6 | I7: =G7-H7 -> 11079.4 | J7: =F7+G7-H7 -> 128086.15 | K7: 28591.7 | L7: 8776.7 | M7: 4592.7 | N7: 117104.38
B8: 6 | C8: Lupin | D8: 2261 | E8: 45.72 | F8: =D8*E8 -> 103372.92 | G8: 6616.18 | H8: 5652.9 | I8: =G8-H8 -> 963.28 | J8: =F8+G8-H8 -> 104336.2 | K8: 29966.58 | L8: 10014.02 | M8: 5550.99 | N8: 104124.35
B9: 7 | C9: Dr Reddy's Labs | D9: 1206 | E9: 83.47 | F9: =D9*E9 -> 100664.82 | G9: 7734.1 | H9: 3348.7 | I9: =G9-H9 -> 4385.4 | J9: =F9+G9-H9 -> 105050.22 | K9: 33227.9 | L9: 6576.6 | M9: 3183.3 | N9: 100750.06
B10: 8 | C10: Mankind Pharma | D10: 2418 | E10: 41.3 | F10: =D10*E10 -> 99863.4 | G10: 6311.54 | H10: 482.77 | I10: =G10-H10 -> 5828.77 | J10: =F10+G10-H10 -> 105692.17 | K10: 14737.88 | L10: 4163.2 | M10: 2067.57 | N10: 99862.42
B11: 9 | C11: Laurus Labs | D11: 1841.05 | E11: 54.03 | F11: =D11*E11 -> 99471.932 | G11: 2518.48 | H11: 113.7 | I11: =G11-H11 -> 2404.78 | J11: =F11+G11-H11 -> 101876.71 | K11: 7269.64 | L11: 2087.55 | M11: 1090.53 | N11: 99474.23
B12: 10 | C12: Aurobindo Pharma | D12: 1656.6 | E12: 58.08 | F12: =D12*E12 -> 96215.328 | G12: 8072.84 | H12: 9870.29 | I12: =G12-H12 -> -1797.45 | J12: =F12+G12-H12 -> 94417.878 | K12: 34935.29 | L12: 7772.84 | M12: 3710.8 | N12: 96334.06
B17: 11 | C17: Biocon | D17: 416 | E17: 162.97 | F17: =D17*E17 -> 67795.52 | G17: 15434.1 | H17: 3193.6 | J17: =F17+G17-H17 -> 80036.02 | K17: 17321.1 | L17: 3853.7 | M17: 416.4 | N17: 67589.7
B18: 12 | C18: Glenmark Pharma. | D18: 2294.25 | E18: 28.22 | F18: =D18*E18 -> 64743.735 | G18: 593.53 | H18: 1176.26 | J18: =F18+G18-H18 -> 64161.005 | K18: 17736.56 | L18: 5296.64 | M18: 1797.79 | N18: 65258.06
B19: 13 | C19: Alkem Lab | D19: 5418.75 | E19: 11.96 | F19: =D19*E19 -> 64808.25 | G19: 2047.16 | H19: 1732.9 | J19: =F19+G19-H19 -> 65122.51 | K19: 14712.27 | L19: 3590.06 | M19: 2351.16 | N19: 64789.27
B20: 14 | C20: Abbott India | D20: 27626 | E20: 2.12 | F20: =D20*E20 -> 58567.12 | G20: 171.99 | H20: 2254.95 | J20: =F20+G20-H20 -> 56484.16 | K20: 7004.38 | L20: 2259.66 | M20: 1614.68 | N20: 58690.86
B21: 15 | C21: Gland Pharma | D21: 2950 | E21: 16.5 | F21: =D21*E21 -> 48675 | G21: 283.59 | H21: 3359.11 | J21: =F21+G21-H21 -> 45599.48 | K21: 6725.3 | L21: 2071.18 | M21: 1128.8 | N21: 48665.14
